{
  "actions": [
    {
      "acted_at": "2011-06-23", 
      "committee": "House Committee on Ways and Means", 
      "references": [], 
      "status": "REFERRED", 
      "text": "Referred to the House Committee on Ways and Means.", 
      "type": "referral"
    }
  ], 
  "amendments": [], 
  "bill_id": "hr2327-112", 
  "bill_type": "hr", 
  "committees": [
    {
      "activity": [
        "referral", 
        "in committee"
      ], 
      "committee": "House Ways and Means", 
      "committee_id": "HSWM"
    }
  ], 
  "congress": "112", 
  "cosponsors": [
    {
      "district": "2", 
      "name": "Amodei, Mark E.", 
      "sponsored_at": "2012-06-05", 
      "state": "NV", 
      "thomas_id": "02090", 
      "title": "Rep", 
      "withdrawn_at": null
    }, 
    {
      "district": "6", 
      "name": "Bartlett, Roscoe G.", 
      "sponsored_at": "2011-06-23", 
      "state": "MD", 
      "thomas_id": "00060", 
      "title": "Rep", 
      "withdrawn_at": null
    }, 
    {
      "district": "50", 
      "name": "Bilbray, Brian P.", 
      "sponsored_at": "2011-06-23", 
      "state": "CA", 
      "thomas_id": "00087", 
      "title": "Rep", 
      "withdrawn_at": null
    }, 
    {
      "district": "45", 
      "name": "Bono Mack, Mary", 
      "sponsored_at": "2011-06-23", 
      "state": "CA", 
      "thomas_id": "01465", 
      "title": "Rep", 
      "withdrawn_at": null
    }, 
    {
      "district": "10", 
      "name": "Broun, Paul C.", 
      "sponsored_at": "2011-06-23", 
      "state": "GA", 
      "thomas_id": "01882", 
      "title": "Rep", 
      "withdrawn_at": null
    }, 
    {
      "district": "6", 
      "name": "Coble, Howard", 
      "sponsored_at": "2011-07-08", 
      "state": "NC", 
      "thomas_id": "00211", 
      "title": "Rep", 
      "withdrawn_at": null
    }, 
    {
      "district": "7", 
      "name": "Culberson, John Abney", 
      "sponsored_at": "2011-06-23", 
      "state": "TX", 
      "thomas_id": "01670", 
      "title": "Rep", 
      "withdrawn_at": null
    }, 
    {
      "district": "19", 
      "name": "Denham, Jeff", 
      "sponsored_at": "2011-07-13", 
      "state": "CA", 
      "thomas_id": "01995", 
      "title": "Rep", 
      "withdrawn_at": null
    }, 
    {
      "district": "3", 
      "name": "Jones, Walter B., Jr.", 
      "sponsored_at": "2011-06-23", 
      "state": "NC", 
      "thomas_id": "00612", 
      "title": "Rep", 
      "withdrawn_at": null
    }, 
    {
      "district": "5", 
      "name": "King, Steve", 
      "sponsored_at": "2011-06-23", 
      "state": "IA", 
      "thomas_id": "01724", 
      "title": "Rep", 
      "withdrawn_at": null
    }, 
    {
      "district": "14", 
      "name": "Mack, Connie", 
      "sponsored_at": "2011-06-23", 
      "state": "FL", 
      "thomas_id": "01776", 
      "title": "Rep", 
      "withdrawn_at": null
    }, 
    {
      "district": "11", 
      "name": "McCotter, Thaddeus G.", 
      "sponsored_at": "2011-07-27", 
      "state": "MI", 
      "thomas_id": "01732", 
      "title": "Rep", 
      "withdrawn_at": null
    }, 
    {
      "district": "1", 
      "name": "Miller, Jeff", 
      "sponsored_at": "2012-06-08", 
      "state": "FL", 
      "thomas_id": "01685", 
      "title": "Rep", 
      "withdrawn_at": null
    }, 
    {
      "district": "12", 
      "name": "Ross, Dennis A.", 
      "sponsored_at": "2012-06-18", 
      "state": "FL", 
      "thomas_id": "02003", 
      "title": "Rep", 
      "withdrawn_at": null
    }, 
    {
      "district": "5", 
      "name": "Thompson, Glenn", 
      "sponsored_at": "2011-06-23", 
      "state": "PA", 
      "thomas_id": "01952", 
      "title": "Rep", 
      "withdrawn_at": null
    }, 
    {
      "district": "3", 
      "name": "Westmoreland, Lynn A.", 
      "sponsored_at": "2011-06-23", 
      "state": "GA", 
      "thomas_id": "01779", 
      "title": "Rep", 
      "withdrawn_at": null
    }
  ], 
  "enacted_as": null, 
  "history": {
    "awaiting_signature": false, 
    "enacted": false, 
    "vetoed": false
  }, 
  "introduced_at": "2011-06-23", 
  "number": "2327", 
  "official_title": "To amend the Internal Revenue Code of 1986 to exclude from gross income gain from the conversion of property by reason of eminent domain.", 
  "popular_title": null, 
  "related_bills": [], 
  "short_title": "Eminent Domain Tax Relief Act of 2011", 
  "sponsor": {
    "district": "11", 
    "name": "Gingrey, Phil", 
    "state": "GA", 
    "thomas_id": "01720", 
    "title": "Rep", 
    "type": "person"
  }, 
  "status": "REFERRED", 
  "status_at": "2011-06-23", 
  "subjects": [
    "Capital gains tax", 
    "Housing finance and home ownership", 
    "Income tax exclusion", 
    "Property rights", 
    "Taxation"
  ], 
  "subjects_top_term": "Taxation", 
  "summary": {
    "as": "Introduced", 
    "date": "2011-06-23", 
    "text": "Eminent Domain Tax Relief Act of 2011 - Amends the Internal Revenue Code to exclude from gross income gain from the conversion of property by reason of eminent domain."
  }, 
  "titles": [
    {
      "as": "introduced", 
      "title": "Eminent Domain Tax Relief Act of 2011", 
      "type": "short"
    }, 
    {
      "as": "introduced", 
      "title": "To amend the Internal Revenue Code of 1986 to exclude from gross income gain from the conversion of property by reason of eminent domain.", 
      "type": "official"
    }
  ], 
  "updated_at": "2013-02-02T22:18:17-05:00"
}