{
  "actions": [
    {
      "acted_at": "2011-01-05", 
      "committee": "House Committee on Ways and Means", 
      "references": [], 
      "status": "REFERRED", 
      "text": "Referred to the House Committee on Ways and Means.", 
      "type": "referral"
    }, 
    {
      "acted_at": "2011-01-14", 
      "in_committee": "House Committee on Ways and Means", 
      "references": [], 
      "subcommittee": "Social Security", 
      "text": "Referred to the Subcommittee on Social Security.", 
      "type": "referral"
    }
  ], 
  "amendments": [], 
  "bill_id": "hr160-112", 
  "bill_type": "hr", 
  "committees": [
    {
      "activity": [
        "referral", 
        "in committee"
      ], 
      "committee": "House Ways and Means", 
      "committee_id": "HSWM"
    }, 
    {
      "activity": [
        "referral"
      ], 
      "committee": "House Ways and Means", 
      "committee_id": "HSWM", 
      "subcommittee": "Subcommittee on Social Security", 
      "subcommittee_id": "01"
    }
  ], 
  "congress": "112", 
  "cosponsors": [], 
  "enacted_as": null, 
  "history": {
    "awaiting_signature": false, 
    "enacted": false, 
    "vetoed": false
  }, 
  "introduced_at": "2011-01-05", 
  "number": "160", 
  "official_title": "To amend title II of the Social Security Act to eliminate the five-month waiting period in the disability insurance program, and for other purposes.", 
  "popular_title": null, 
  "related_bills": [], 
  "short_title": "Social Security Fairness for the Terminally Ill Act of 2011", 
  "sponsor": {
    "district": "11", 
    "name": "Shuler, Heath", 
    "state": "NC", 
    "thomas_id": "01859", 
    "title": "Rep", 
    "type": "person"
  }, 
  "status": "REFERRED", 
  "status_at": "2011-01-05", 
  "subjects": [
    "Long-term, rehabilitative, and terminal care", 
    "Social security and elderly assistance", 
    "Social welfare"
  ], 
  "subjects_top_term": "Social welfare", 
  "summary": {
    "as": "Introduced", 
    "date": "2011-01-05", 
    "text": "Social Security Fairness for the Terminally Ill Act of 2011 - Amends title II (Old Age, Survivors and Disability Insurance) (OASDI) of the Social Security Act to eliminate the waiting period for disability insurance benefits for terminally ill individuals."
  }, 
  "titles": [
    {
      "as": "introduced", 
      "title": "Social Security Fairness for the Terminally Ill Act of 2011", 
      "type": "short"
    }, 
    {
      "as": "introduced", 
      "title": "To amend title II of the Social Security Act to eliminate the five-month waiting period in the disability insurance program, and for other purposes.", 
      "type": "official"
    }
  ], 
  "updated_at": "2013-02-02T21:52:30-05:00"
}