{
  "actions": [
    {
      "acted_at": "1989-01-25", 
      "committee": "Committee on Appropriations", 
      "references": [], 
      "status": "REFERRED", 
      "text": "Read twice and referred to the Committee on Appropriations.", 
      "type": "referral"
    }
  ], 
  "amendments": [], 
  "bill_id": "s26-101", 
  "bill_type": "s", 
  "committees": [
    {
      "activity": [
        "referral", 
        "in committee"
      ], 
      "committee": "Senate Appropriations", 
      "committee_id": "SSAP"
    }
  ], 
  "congress": "101", 
  "cosponsors": [
    {
      "district": null, 
      "name": "Coats, Daniel", 
      "sponsored_at": "1989-04-04", 
      "state": "IN", 
      "thomas_id": "00209", 
      "title": "Sen", 
      "withdrawn_at": null
    }, 
    {
      "district": null, 
      "name": "Cranston, Alan", 
      "sponsored_at": "1989-01-31", 
      "state": "CA", 
      "thomas_id": "01311", 
      "title": "Sen", 
      "withdrawn_at": null
    }, 
    {
      "district": null, 
      "name": "D'Amato, Alfonse", 
      "sponsored_at": "1989-01-31", 
      "state": "NY", 
      "thomas_id": "01313", 
      "title": "Sen", 
      "withdrawn_at": null
    }, 
    {
      "district": null, 
      "name": "DeConcini, Dennis", 
      "sponsored_at": "1989-01-31", 
      "state": "AZ", 
      "thomas_id": "01315", 
      "title": "Sen", 
      "withdrawn_at": null
    }, 
    {
      "district": null, 
      "name": "Gore, Albert, Jr.", 
      "sponsored_at": "1989-04-04", 
      "state": "TN", 
      "thomas_id": "00449", 
      "title": "Sen", 
      "withdrawn_at": null
    }, 
    {
      "district": null, 
      "name": "Graham, Bob", 
      "sponsored_at": "1989-01-31", 
      "state": "FL", 
      "thomas_id": "01342", 
      "title": "Sen", 
      "withdrawn_at": null
    }, 
    {
      "district": null, 
      "name": "Kerry, John F.", 
      "sponsored_at": "1989-01-31", 
      "state": "MA", 
      "thomas_id": "01379", 
      "title": "Sen", 
      "withdrawn_at": null
    }, 
    {
      "district": null, 
      "name": "Lieberman, Joseph I.", 
      "sponsored_at": "1989-01-31", 
      "state": "CT", 
      "thomas_id": "01385", 
      "title": "Sen", 
      "withdrawn_at": null
    }, 
    {
      "district": null, 
      "name": "Nunn, Sam", 
      "sponsored_at": "1989-01-31", 
      "state": "GA", 
      "thomas_id": "01413", 
      "title": "Sen", 
      "withdrawn_at": null
    }, 
    {
      "district": null, 
      "name": "Pell, Claiborne", 
      "sponsored_at": "1989-03-15", 
      "state": "RI", 
      "thomas_id": "01417", 
      "title": "Sen", 
      "withdrawn_at": null
    }, 
    {
      "district": null, 
      "name": "Riegle, Donald W., Jr.", 
      "sponsored_at": "1989-03-15", 
      "state": "MI", 
      "thomas_id": "00961", 
      "title": "Sen", 
      "withdrawn_at": null
    }, 
    {
      "district": null, 
      "name": "Wilson, Pete", 
      "sponsored_at": "1989-01-25", 
      "state": "CA", 
      "thomas_id": "01456", 
      "title": "Sen", 
      "withdrawn_at": null
    }
  ], 
  "enacted_as": null, 
  "history": {
    "awaiting_signature": false, 
    "enacted": false, 
    "vetoed": false
  }, 
  "introduced_at": "1989-01-25", 
  "number": "26", 
  "official_title": "A bill to make certain supplemental appropriations in order to fully fund the Anti-Drug Abuse Act of 1988.", 
  "popular_title": null, 
  "related_bills": [
    {
      "bill_id": "hr705-101", 
      "reason": "identical"
    }
  ], 
  "short_title": "Anti-Drug Abuse Supplemental Appropriations Act of 1989", 
  "sponsor": {
    "district": null, 
    "name": "Moynihan, Daniel Patrick", 
    "state": "NY", 
    "thomas_id": "01407", 
    "title": "Sen", 
    "type": "person"
  }, 
  "status": "REFERRED", 
  "status_at": "1989-01-25", 
  "subjects": [
    "Alcoholism", 
    "American economic assistance", 
    "American military assistance", 
    "Appellate courts", 
    "Coast guard", 
    "Colombia", 
    "Correctional institutions", 
    "Customs administration", 
    "District courts", 
    "Drug abuse", 
    "Drugs", 
    "Drugs and employment", 
    "Drugs and youth", 
    "Drunk driving", 
    "Education", 
    "Employee assistance programs", 
    "Federal advisory bodies", 
    "Federal aid to Indians", 
    "Federal aid to alcoholism programs", 
    "Federal aid to education", 
    "Federal receipts and expenditures", 
    "Government operations and politics", 
    "Health education", 
    "Juries", 
    "Law enforcement officers", 
    "Narcotic traffic", 
    "National forests", 
    "National parks", 
    "Prisoners", 
    "Public housing", 
    "Public lands and natural resources", 
    "Supplemental appropriations", 
    "Territories (U.S.)", 
    "Treatment and rehabilitation of alcoholics", 
    "Treatment and rehabilitation of narcotic addicts", 
    "Veterans' medical care"
  ], 
  "subjects_top_term": "Drugs", 
  "summary": {
    "as": "Introduced", 
    "date": "1989-01-25", 
    "text": "Anti-Drug Abuse Supplemental Appropriations Act of 1989 - Makes supplemental appropriations for FY 1989 for purposes specified in titles I through VIII and for drug treatment and rehabilitation services and assistance to law enforcement agencies. Title I: Departments of Justice and State and the Judiciary - Makes appropriations for the Department of Justice for: (1) salaries and expenses for the Federal Bureau of Investigation, the Drug Enforcement Administration, the Immigration and Naturalization Service, the General Legal Activities Account, U.S. Attorneys, the U.S. Marshals Service, and the Federal Prison System (FPS); (2) support of U.S. prisoners; (3) buildings and facilities of the FPS; (4) the National Institute of Corrections; (5) Office of Justice programs; (6) the National Institute of Justice; (7) the Bureau of Justice Statistics; (8) the Office of Juvenile Justice and Delinquency Prevention; (9) the Bureau of Justice Assistance; and (10) the State Justice Institute. Makes appropriations for the Department of State for: (1) expenses for development, procurement, and implementation of a machine-readable travel and identity document border security program; and (2) rewards for information concerning narcotics-related offenses. Makes appropriations for the Judiciary for: (1) salaries and expenses for courts of appeals, district courts, and other judicial services; (2) defender services; (3) fees of jurors and commissioners; and (4) security equipment. Title II: Departments of Labor, Health and Human Services, and Related Agencies - Makes appropriations for: (1) the Department of Labor for substance abuse employee assistance programs in the workplace; (2) the Department of Health and Human Services for certain substance abuse prevention and treatment activities; (3) the Department of Education for school improvement programs and for the National Commission on Drug-Free Schools; and (4) related agency substance abuse prevention and education activities. Title III: Department of Agriculture - Makes appropriations to the Department of Agriculture for: (1) the Food and Nutrition Service for preparing and distributing drug abuse education materials; and (2) the National Forest Service for Federal law enforcement activities relating to the use and production of narcotics and controlled substances on lands administered by the Service. Title IV: Department of Transportation - Makes appropriations to the Department of Transportation for: (1) the Coast Guard for drug interdiction program operating expenses; (2) acquisition, construction, and improvements; (3) the Federal Highway Administration for drunk driving prevention programs; and (4) the National Highway Traffic Safety Administration to establish a regional pilot program for training law enforcement officers to identify individuals operating a motor vehicle while under the influence of alcohol or controlled substances. Title V: Department of the Treasury - Makes appropriations to the Department of the Treasury for: (1) salaries and expenses for the Bureau of Alcohol, Tobacco and Firearms; (2) salaries and expenses for the U.S. Customs Service, including funding for development, procurement, and implementation of a machine-readable travel and identity document border security program; (3) operations and maintenance for the Customs Service's air interdiction program; and (4) the Federal law Enforcement Training Center. Makes appropriations for: (1) the National Commission on Measured Responses to Achieve a Drug-Free America by 1995; and (2) the President's Media Commission on Alcohol and Drug Abuse Prevention. Title VI: Foreign Assistance - Makes appropriations to the Department of State for: (1) multilateral assistance authorized by the International Narcotics Control Act of 1988; and (2) military assistance to the armed forces of Colombia to combat illicit narcotics production and trafficking. Title VII: Departments of Housing and Urban Development and Veterans Affairs - Makes appropriations to the: (1) Department of Housing and Urban Development for the Public Housing Drug Elimination Pilot Program; and (2) Department of Veterans Affairs for drug and alcohol treatment programs. Title VIII: Department of the Interior - Makes appropriations for: (1) Indian alcohol and substance abuse prevention and treatment; (2) Federal law enforcement activities related to the use and production of narcotics and controlled substances on Bureau of Land Management public lands and in National Park System units; and (3) grants to the Governments of American Samoa, Guam, the Northern Mariana Islands, Puerto Rico, the Virgin Islands, and Palau for specified anti-drug abuse purposes under the United States Insular Areas Drug Abuse Act of 1986. Title IX: General Provisions - Precludes any part of any appropriation contained in this Act from remaining available for obligation beyond the current fiscal year unless expressly so provided. Expresses the sense of the Congress that Federal anti-drug abuse program funding levels for FY 1990 should be maintained at the FY 1989 levels provided under specified Acts together with increases authorized by the Anti-Drug Abuse Act of 1988."
  }, 
  "titles": [
    {
      "as": "introduced", 
      "title": "Anti-Drug Abuse Supplemental Appropriations Act of 1989", 
      "type": "short"
    }, 
    {
      "as": "introduced", 
      "title": "A bill to make certain supplemental appropriations in order to fully fund the Anti-Drug Abuse Act of 1988.", 
      "type": "official"
    }
  ], 
  "updated_at": "2013-02-02T20:05:04-05:00"
}