{
  "actions": [
    {
      "acted_at": "1995-03-06", 
      "references": [
        {
          "reference": "CR S3522", 
          "type": null
        }
      ], 
      "text": "Sponsor introductory remarks on measure.", 
      "type": "action"
    }, 
    {
      "acted_at": "1995-03-06", 
      "committee": "Committee on Finance", 
      "references": [], 
      "status": "REFERRED", 
      "text": "Read twice and referred to the Committee on Finance.", 
      "type": "referral"
    }
  ], 
  "amendments": [], 
  "bill_id": "s502-104", 
  "bill_type": "s", 
  "committees": [
    {
      "activity": [
        "referral", 
        "in committee"
      ], 
      "committee": "Senate Finance", 
      "committee_id": "SSFI"
    }
  ], 
  "congress": "104", 
  "cosponsors": [
    {
      "district": null, 
      "name": "Lieberman, Joseph I.", 
      "sponsored_at": "1995-03-06", 
      "state": "CT", 
      "thomas_id": "01385", 
      "title": "Sen", 
      "withdrawn_at": null
    }
  ], 
  "enacted_as": null, 
  "history": {
    "awaiting_signature": false, 
    "enacted": false, 
    "vetoed": false
  }, 
  "introduced_at": "1995-03-06", 
  "number": "502", 
  "official_title": "A bill to clarify the tax treatment of certain disability benefits received by former police officers or firefighters.", 
  "popular_title": null, 
  "related_bills": [], 
  "short_title": null, 
  "sponsor": {
    "district": null, 
    "name": "Dodd, Christopher J.", 
    "state": "CT", 
    "thomas_id": "00302", 
    "title": "Sen", 
    "type": "person"
  }, 
  "status": "REFERRED", 
  "status_at": "1995-03-06", 
  "subjects": [
    "Crime and law enforcement", 
    "Disabled", 
    "Emergency management", 
    "Fire fighters", 
    "Government operations and politics", 
    "Health", 
    "Heart diseases", 
    "Hypertension", 
    "Income tax", 
    "Labor and employment", 
    "Law", 
    "Limitation of actions", 
    "Local officials and employees", 
    "Police", 
    "State officials and employees", 
    "Survivors' benefits", 
    "Tax credits", 
    "Tax exclusion", 
    "Tax refunds", 
    "Taxation", 
    "Workers' compensation"
  ], 
  "subjects_top_term": "Income tax", 
  "summary": {
    "as": "Introduced", 
    "date": "1995-03-06", 
    "text": "Treats heart disease and hypertension as personal injuries or sickness for purposes of excluding from gross income under the Internal Revenue Code the disability benefits received by former police officers or fire fighters."
  }, 
  "titles": [
    {
      "as": "introduced", 
      "title": "A bill to clarify the tax treatment of certain disability benefits received by former police officers or firefighters.", 
      "type": "official"
    }
  ], 
  "updated_at": "2013-02-02T20:32:41-05:00"
}